open_agent/__init__.py
open_agent/agent.py
open_agent/config.json
open_agent/version.py
open_agent-0.1.195.dist-info/METADATA
open_agent-0.1.195.dist-info/WHEEL
open_agent-0.1.195.dist-info/top_level.txt
open_agent-0.1.195.dist-info/RECORD
