Metadata-Version: 2.1
Name: open-agent
Version: 0.1.195
Summary: An Autonomous Vehicle Agent for SMARTS built using OpEn
Home-page: UNKNOWN
License: UNKNOWN
Platform: UNKNOWN
Requires-Dist: opengen (==0.6.4)
Requires-Dist: smarts
Requires-Dist: wheel
Requires-Dist: maturin
Requires-Dist: python-bindings-open-agent-solver
